tests/__init__.py
tests/test__sid_to_key.py
tests/test_translate.py
yandexfreetranslate/__init__.py
yandexfreetranslate/utils.py
yandexfreetranslate-1.5.dist-info/LICENSE
yandexfreetranslate-1.5.dist-info/METADATA
yandexfreetranslate-1.5.dist-info/WHEEL
yandexfreetranslate-1.5.dist-info/top_level.txt
yandexfreetranslate-1.5.dist-info/RECORD
