Metadata-Version: 2.1
Name: yandexfreetranslate
Version: 1.5
Summary: UNKNOWN
Home-page: https://github.com/alekssamos/yandexfreetranslate/
Author: alekssamos
Author-email: aleks-samos@yandex.ru
License: UNKNOWN
Platform: UNKNOWN
